dlatk/DDLA.py
dlatk/__init__.py
dlatk/classifyPredictor.py
dlatk/dimensionReducer.py
dlatk/dlaConstants.py
dlatk/dlaWorker.py
dlatk/featureExtractor.py
dlatk/featureGetter.py
dlatk/featureRefiner.py
dlatk/featureStar.py
dlatk/mediation.py
dlatk/messageAnnotator.py
dlatk/messageTransformer.py
dlatk/occurrenceSelection.py
dlatk/outcomeAnalyzer.py
dlatk/outcomeGetter.py
dlatk/pca_mod.py
dlatk/regressionPredictor.py
dlatk/semanticsExtractor.py
dlatk/textCleaner.py
dlatk/topicExtractor.py
dlatk/data/dla_tutorial.sql
dlatk/data/dlatk_lexica.sql
dlatk/lexicainterface/__init__.py
dlatk/lexicainterface/lexInterface.py
dlatk/lib/StanfordParser.py
dlatk/lib/TweetNLP.py
dlatk/lib/__init__.py
dlatk/lib/descStats.py
dlatk/lib/happierfuntokenizing.py
dlatk/lib/wc_tools.py
dlatk/lib/wordcloud.py
dlatk/mysqlmethods/__init__.py
dlatk/mysqlmethods/mysqlMethods.py
dlatk/mysqlmethods/mysql_iter_funcs.py
dlatk/tools/__init__.py
dlatk-1.1.8.data/scripts/dlatkInterface.py
dlatk-1.1.8.dist-info/METADATA
dlatk-1.1.8.dist-info/RECORD
dlatk-1.1.8.dist-info/WHEEL
dlatk-1.1.8.dist-info/top_level.txt
