Metadata-Version: 2.1
Name: dlatk
Version: 1.1.8
Summary: DLATK is an end to end human text analysis package, specifically suited for social media and social scientific applications. It is written in Python 3 and developed by the World Well-Being Project at the University of Pennsylvania and Stony Brook University. 
Home-page: http://dlatk.wwbp.org
Author: H. Andrew Schwartz, Salvatore Giorgi, Maarten Sap, Patrick Crutchley, Lukasz Dziurzynski and Megha Agrawal
Author-email: has@cs.stonybrook.edu, sgiorgi@sas.upenn.edu
License: GNU General Public License v3 (GPLv3)
Download-URL: https://github.com/dlatk/dlatk
Platform: UNKNOWN
Classifier: Environment :: Console
Classifier: Natural Language :: English
Classifier: Intended Audience :: End Users/Desktop
Classifier: Intended Audience :: Developers
Classifier: Intended Audience :: Science/Research
Classifier: Programming Language :: Python
Classifier: Programming Language :: Python :: 3
Classifier: Programming Language :: Python :: 3.5
Classifier: Topic :: Scientific/Engineering
Provides-Extra: textstat
Provides-Extra: rpy2
Provides-Extra: wordcloud
Provides-Extra: jsonrpclib-pelix
Provides-Extra: image
Provides-Extra: simplejson
Provides-Extra: langid
Requires-Dist: matplotlib (>=1.3.1)
Requires-Dist: mysqlclient
Requires-Dist: nltk (>=3.2.1)
Requires-Dist: numpy
Requires-Dist: pandas (>=0.20.3)
Requires-Dist: patsy (>=0.2.1)
Requires-Dist: python-dateutil (>=2.5.0)
Requires-Dist: scikit-learn (==0.18.2)
Requires-Dist: scipy (>=0.19.1)
Requires-Dist: SQLAlchemy (>=1.0.13)
Requires-Dist: statsmodels (>=0.8.0)
Provides-Extra: image
Requires-Dist: image; extra == 'image'
Provides-Extra: jsonrpclib-pelix
Requires-Dist: jsonrpclib-pelix (>=0.2.8); extra == 'jsonrpclib-pelix'
Provides-Extra: langid
Requires-Dist: langid (>=1.1.4); extra == 'langid'
Provides-Extra: rpy2
Requires-Dist: rpy2; extra == 'rpy2'
Provides-Extra: simplejson
Requires-Dist: simplejson (>=3.3.1); extra == 'simplejson'
Provides-Extra: textstat
Requires-Dist: textstat (>=0.6.1); extra == 'textstat'
Provides-Extra: wordcloud
Requires-Dist: wordcloud (==1.1.3); extra == 'wordcloud'
